data/__init__.py
data/download_cub.py
data/download_mnist.py
data/download_shapes.py
deep_logic/__init__.py
deep_logic/_version.py
deep_logic/concept_extractor/__init__.py
deep_logic/concept_extractor/cnn_models.py
deep_logic/concept_extractor/concept_extractor.py
deep_logic/logic/__init__.py
deep_logic/logic/base.py
deep_logic/logic/layer.py
deep_logic/logic/metrics.py
deep_logic/logic/psi_nn.py
deep_logic/logic/relu_nn.py
deep_logic/logic/relunn.py
deep_logic/logic/sigmoidnn.py
deep_logic/models/__init__.py
deep_logic/models/base.py
deep_logic/models/brl.py
deep_logic/models/general_nn.py
deep_logic/models/logistic_regression.py
deep_logic/models/psi_nn.py
deep_logic/models/relu_nn.py
deep_logic/models/tree.py
deep_logic/models/ext_models/__init__.py
deep_logic/models/ext_models/brl/BigDataRuleListClassifier.py
deep_logic/models/ext_models/brl/RuleListClassifier.py
deep_logic/models/ext_models/brl/__init__.py
deep_logic/models/ext_models/brl/Discretization/Entropy.py
deep_logic/models/ext_models/brl/Discretization/MDLP.py
deep_logic/models/ext_models/brl/Discretization/__init__.py
deep_logic/models/ext_models/brl/LethamBRL/BRL_code.py
deep_logic/models/ext_models/brl/LethamBRL/__init__.py
deep_logic/models/ext_models/brl/examples/__init__.py
deep_logic/models/ext_models/brl/examples/demo.py
deep_logic/models/ext_models/brl/examples/diabetes_demo.py
deep_logic/nn/__init__.py
deep_logic/nn/concepts.py
deep_logic/nn/linear.py
deep_logic/nn/logic.py
deep_logic/utils/__init__.py
deep_logic/utils/base.py
deep_logic/utils/data.py
deep_logic/utils/datasets.py
deep_logic/utils/general_nn.py
deep_logic/utils/layer.py
deep_logic/utils/loss.py
deep_logic/utils/metrics.py
deep_logic/utils/psi_nn.py
deep_logic/utils/relu_nn.py
deep_logic/utils/relunn.py
deep_logic/utils/selection.py
deep_logic/utils/sigmoidnn.py
tests/__init__.py
tests/test_functions.py
tests/test_functions_cuda.py
deep_logic-4.0.3.dist-info/LICENSE
deep_logic-4.0.3.dist-info/METADATA
deep_logic-4.0.3.dist-info/WHEEL
deep_logic-4.0.3.dist-info/top_level.txt
deep_logic-4.0.3.dist-info/RECORD
